azure/mgmt/hdinsight/__init__.py
azure/mgmt/hdinsight/_configuration.py
azure/mgmt/hdinsight/_hd_insight_management_client.py
azure/mgmt/hdinsight/_version.py
azure/mgmt/hdinsight/aio/__init__.py
azure/mgmt/hdinsight/aio/_configuration.py
azure/mgmt/hdinsight/aio/_hd_insight_management_client.py
azure/mgmt/hdinsight/aio/operations/__init__.py
azure/mgmt/hdinsight/aio/operations/_applications_operations.py
azure/mgmt/hdinsight/aio/operations/_clusters_operations.py
azure/mgmt/hdinsight/aio/operations/_configurations_operations.py
azure/mgmt/hdinsight/aio/operations/_extensions_operations.py
azure/mgmt/hdinsight/aio/operations/_locations_operations.py
azure/mgmt/hdinsight/aio/operations/_operations.py
azure/mgmt/hdinsight/aio/operations/_script_actions_operations.py
azure/mgmt/hdinsight/aio/operations/_script_execution_history_operations.py
azure/mgmt/hdinsight/aio/operations/_virtual_machines_operations.py
azure/mgmt/hdinsight/models/__init__.py
azure/mgmt/hdinsight/models/_hd_insight_management_client_enums.py
azure/mgmt/hdinsight/models/_models.py
azure/mgmt/hdinsight/models/_models_py3.py
azure/mgmt/hdinsight/operations/__init__.py
azure/mgmt/hdinsight/operations/_applications_operations.py
azure/mgmt/hdinsight/operations/_clusters_operations.py
azure/mgmt/hdinsight/operations/_configurations_operations.py
azure/mgmt/hdinsight/operations/_extensions_operations.py
azure/mgmt/hdinsight/operations/_locations_operations.py
azure/mgmt/hdinsight/operations/_operations.py
azure/mgmt/hdinsight/operations/_script_actions_operations.py
azure/mgmt/hdinsight/operations/_script_execution_history_operations.py
azure/mgmt/hdinsight/operations/_virtual_machines_operations.py
azure_mgmt_hdinsight-8.0.0.dist-info/METADATA
azure_mgmt_hdinsight-8.0.0.dist-info/WHEEL
azure_mgmt_hdinsight-8.0.0.dist-info/top_level.txt
azure_mgmt_hdinsight-8.0.0.dist-info/RECORD
